{
  "required": true,
  "$schema": "http://json-schema.org/draft-03/schema",
  "type": "array",
  "title": "Events and dates",
  "items": {
    "type": "object",
    "properties": {
      "dates": {
        "required": true,
        "$schema": "http://json-schema.org/draft-03/schema",
        "type": "array",
        "items": { "$ref": "date.json" }
      },
      "events": {
        "required": true,
        "$schema": "http://json-schema.org/draft-03/schema",
        "type": "array",
        "items": { "$ref": "event.json" }
      }
    }
  }
}
